kivy_garden/tickmarker/__init__.py
kivy_garden/tickmarker/_version.py
kivy_garden/tickmarker/ticks.cp39-win32.pyd
kivy_garden/tickmarker/tests/test_import.py
kivy_garden.tickmarker-3.0.1.dist-info/AUTHORS.txt
kivy_garden.tickmarker-3.0.1.dist-info/LICENSE.txt
kivy_garden.tickmarker-3.0.1.dist-info/METADATA
kivy_garden.tickmarker-3.0.1.dist-info/WHEEL
kivy_garden.tickmarker-3.0.1.dist-info/top_level.txt
kivy_garden.tickmarker-3.0.1.dist-info/RECORD
